src/__init__.py
pyeeg-0.0.2.dist-info/LICENCE.txt
pyeeg-0.0.2.dist-info/METADATA
pyeeg-0.0.2.dist-info/WHEEL
pyeeg-0.0.2.dist-info/top_level.txt
pyeeg-0.0.2.dist-info/RECORD
