Metadata-Version: 2.1
Name: pyeeg
Version: 0.0.2
Summary: A Library for the Emotiv Insight Five Channel EEG.
Home-page: UNKNOWN
Author: Jannis Biedermann
Author-email: henrikejannis@gmail.com
License: MIT
Keywords: eeg
Platform: UNKNOWN
Classifier: Development Status :: 5 - Production/Stable
Classifier: Intended Audience :: Education
Classifier: Operating System :: Microsoft :: Windows :: Windows 10
Classifier: License :: OSI Approved :: MIT License
Classifier: Programming Language :: Python :: 3
Requires-Dist: websocket
Requires-Dist: websocket-client
